blackPanther_pydialog/__init__.py
blackPanther_pydialog/window1.py
blackPanther_pydialog-0.9.8.data/scripts/pydialog
pydialog/window1.py
blackPanther_pydialog-0.9.8.dist-info/LICENSE
blackPanther_pydialog-0.9.8.dist-info/METADATA
blackPanther_pydialog-0.9.8.dist-info/WHEEL
blackPanther_pydialog-0.9.8.dist-info/top_level.txt
blackPanther_pydialog-0.9.8.dist-info/RECORD
